noicelink/__init__.py
noicelink/noicelink.py
noicelink-1.0.dist-info/LICENSE
noicelink-1.0.dist-info/METADATA
noicelink-1.0.dist-info/WHEEL
noicelink-1.0.dist-info/top_level.txt
noicelink-1.0.dist-info/RECORD
